automatheque/__init__.py
automatheque/schema/__init__.py
automatheque/schema/base.py
automatheque/schema/etiquettes.py
automatheque/schema/medium.py
automatheque/schema/meta_attr.py
automatheque/schema/py.typed
automatheque/schema/audio/__init__.py
automatheque/schema/audio/chanson.py
automatheque/schema/audio/tags.py
automatheque/schema/calendrier/__init__.py
automatheque/schema/calendrier/evenement.py
automatheque/schema/geolocalisation/__init__.py
automatheque/schema/geolocalisation/emplacement.py
automatheque/schema/image/__init__.py
automatheque/schema/image/identificateurs_photo.py
automatheque/schema/image/photo.py
automatheque/schema/image/tags.py
automatheque/schema/texte/__init__.py
automatheque/schema/texte/courriel.py
automatheque/schema/texte/nfo.py
automatheque/schema/texte/soustitre.py
automatheque/schema/texte/syndication.py
automatheque/schema/video/__init__.py
automatheque/schema/video/episode.py
automatheque/schema/video/film.py
automatheque/schema/video/serie.py
schema/__init__.py
schema/base.py
schema/etiquettes.py
schema/medium.py
schema/meta_attr.py
schema/audio/__init__.py
schema/audio/chanson.py
schema/audio/tags.py
schema/calendrier/__init__.py
schema/calendrier/evenement.py
schema/geolocalisation/__init__.py
schema/geolocalisation/emplacement.py
schema/image/__init__.py
schema/image/identificateurs_photo.py
schema/image/photo.py
schema/image/tags.py
schema/texte/__init__.py
schema/texte/courriel.py
schema/texte/nfo.py
schema/texte/soustitre.py
schema/texte/syndication.py
schema/video/__init__.py
schema/video/episode.py
schema/video/film.py
schema/video/serie.py
automatheque.schema-0.9.7.dist-info/METADATA
automatheque.schema-0.9.7.dist-info/WHEEL
automatheque.schema-0.9.7.dist-info/top_level.txt
automatheque.schema-0.9.7.dist-info/RECORD
