Metadata-Version: 2.1
Name: automatheque.schema
Version: 0.9.7
Summary: Domaine pour des classes courantes et partagées
Author-email: Marc <githubmarc@maj44.com>
License: GPLv3.0
Project-URL: Home, https://github.com/jaegerbobomb/automatheque
Project-URL: Repository, https://github.com/jaegerbobomb/automatheque.git
Requires-Python: >=3.8
Requires-Dist: attrs
Provides-Extra: dev
Requires-Dist: pytest ; extra == 'dev'
Requires-Dist: tox ; extra == 'dev'
